backend_sqlalchemy/__init__.py
backend_sqlalchemy/main.py
backend_sqlalchemy/mixins.py
backend_sqlalchemy-0.1.5.dist-info/METADATA
backend_sqlalchemy-0.1.5.dist-info/WHEEL
backend_sqlalchemy-0.1.5.dist-info/RECORD
